setup.py
max/__about__.py
max/__init__.py
max/config.py
max/create.py
max/run.py
max/Installtest/__init__.py
max/Installtest/findapp.py
max/Installtest/installapp.py
max/checker/__init__.py
max/checker/checkapp.py
max/checker/client.py
max/checker/config.py
max/checker/filetools.py
max/checker/findapp.py
max/checker/getdata.py
max/checker/loggers.py
max/checker/run.py
max/checker/server.py
max/lanuchtest/__init__.py
max/lanuchtest/lanuchapp.py
max/logintest/__init__.py
max/logintest/location.py
max/logintest/logintest.py
max/monkey/__init__.py
max/monkey/common.py
max/monkey/getbasic.py
max/monkey/getcpu.py
max/monkey/getfps.py
max/monkey/getmem.py
max/monkey/getnetwork.py
max/monkey/monkey.py
max/report/__init__.py
max/report/findapp.py
max/report/getdata.py
max/report/mailconfig.py
max/report/predata.py
max/report/sendmail.py
max/report/backup/__init__.py
max/report/backup/client.py
max/report/backup/server.py
max/tools/__init__.py
max/tools/filetools.py
max/tools/loggers.py
maxauto.egg-info/PKG-INFO
maxauto.egg-info/SOURCES.txt
maxauto.egg-info/dependency_links.txt
maxauto.egg-info/entry_points.txt
maxauto.egg-info/requires.txt
maxauto.egg-info/top_level.txt