Metadata-Version: 1.2
Name: maxauto
Version: 1.0.1
Summary: maxauto
Home-page: https://github.com/xinxi1990/maxauto
Author: xinxi
Author-email: xinxi1990@163.com
License: MIT
Keywords: pip,maxauto,monkey
Platform: any
Classifier: Development Status :: 3 - Alpha
Classifier: Programming Language :: Python :: 2.7
Classifier: Programming Language :: Python :: 3.4
Classifier: Programming Language :: Python :: 3.5
Classifier: Programming Language :: Python :: 3.6
Requires-Python: >=2.7, !=3.0.*, !=3.1.*, !=3.2.*, !=3.3.*, <4
